{
  "inputs": [
    {
      "flag": "dkim1",
      "name": "DKIM CNAME 1 value",
      "env": "SENDGRID_DKIM1",
      "example": "s1.domainkey.u12345.wl.sendgrid.net",
      "instructions": "In the SendGrid dashboard, go to Settings > Sender Authentication > Domain Authentication, set up your domain, and copy the value for the 's1._domainkey' CNAME record."
    },
    {
      "flag": "dkim2",
      "name": "DKIM CNAME 2 value",
      "env": "SENDGRID_DKIM2",
      "example": "s2.domainkey.u12345.wl.sendgrid.net",
      "instructions": "In the SendGrid dashboard, go to Settings > Sender Authentication > Domain Authentication, and copy the value for the 's2._domainkey' CNAME record."
    }
  ],
  "records": [
    { "type": "TXT",   "name": "@",             "value": "v=spf1 include:sendgrid.net ~all" },
    { "type": "TXT",   "name": "_dmarc",         "value": "v=DMARC1; p=none;" },
    { "type": "CNAME", "name": "s1._domainkey",  "value": "{DKIM1}" },
    { "type": "CNAME", "name": "s2._domainkey",  "value": "{DKIM2}" }
  ]
}
